{
  "main": {
    "id": "7b82fd17fd8d3787",
    "type": "split",
    "children": [
      {
        "id": "b537835a6909008c",
        "type": "tabs",
        "children": [
          {
            "id": "555153a2d7e271b6",
            "type": "leaf",
            "state": {
              "type": "markdown",
              "state": {
                "file": "Linux Commands.md",
                "mode": "source",
                "source": false
              },
              "icon": "lucide-file",
              "title": "Linux Commands"
            }
          }
        ]
      }
    ],
    "direction": "vertical"
  },
  "left": {
    "id": "bc1db3765bb4ea97",
    "type": "split",
    "children": [
      {
        "id": "d82fa05cfa5a4406",
        "type": "tabs",
        "children": [
          {
            "id": "e96b12759824060b",
            "type": "leaf",
            "state": {
              "type": "file-explorer",
              "state": {
                "sortOrder": "alphabetical",
                "autoReveal": false
              },
              "icon": "lucide-folder-closed",
              "title": "Files"
            }
          },
          {
            "id": "0ada294057038ef2",
            "type": "leaf",
            "state": {
              "type": "search",
              "state": {
                "query": "",
                "matchingCase": false,
                "explainSearch": false,
                "collapseAll": false,
                "extraContext": false,
                "sortOrder": "alphabetical"
              },
              "icon": "lucide-search",
              "title": "Search"
            }
          },
          {
            "id": "1f48caa775796f51",
            "type": "leaf",
            "state": {
              "type": "bookmarks",
              "state": {},
              "icon": "lucide-bookmark",
              "title": "Bookmarks"
            }
          }
        ]
      }
    ],
    "direction": "horizontal",
    "width": 300
  },
  "right": {
    "id": "21c0a5a91649e0c3",
    "type": "split",
    "children": [
      {
        "id": "1b716e622448a700",
        "type": "tabs",
        "children": [
          {
            "id": "446f3d9afc24ce10",
            "type": "leaf",
            "state": {
              "type": "backlink",
              "state": {
                "file": "Linux Commands.md",
                "collapseAll": false,
                "extraContext": false,
                "sortOrder": "alphabetical",
                "showSearch": false,
                "searchQuery": "",
                "backlinkCollapsed": false,
                "unlinkedCollapsed": true
              },
              "icon": "links-coming-in",
              "title": "Backlinks for Linux Commands"
            }
          },
          {
            "id": "60b1ee787f8397c9",
            "type": "leaf",
            "state": {
              "type": "outgoing-link",
              "state": {
                "file": "Linux Commands.md",
                "linksCollapsed": false,
                "unlinkedCollapsed": true
              },
              "icon": "links-going-out",
              "title": "Outgoing links from Linux Commands"
            }
          },
          {
            "id": "3a6942c9dc66ad3e",
            "type": "leaf",
            "state": {
              "type": "tag",
              "state": {
                "sortOrder": "frequency",
                "useHierarchy": true,
                "showSearch": false,
                "searchQuery": ""
              },
              "icon": "lucide-tags",
              "title": "Tags"
            }
          },
          {
            "id": "70f3cf35f78d9c82",
            "type": "leaf",
            "state": {
              "type": "outline",
              "state": {
                "file": "Linux Commands.md",
                "followCursor": false,
                "showSearch": false,
                "searchQuery": ""
              },
              "icon": "lucide-list",
              "title": "Outline of Linux Commands"
            }
          }
        ]
      }
    ],
    "direction": "horizontal",
    "width": 300,
    "collapsed": true
  },
  "left-ribbon": {
    "hiddenItems": {
      "switcher:Open quick switcher": false,
      "graph:Open graph view": false,
      "canvas:Create new canvas": false,
      "daily-notes:Open today's daily note": false,
      "templates:Insert template": false,
      "command-palette:Open command palette": false,
      "bases:Create new base": false
    }
  },
  "active": "555153a2d7e271b6",
  "lastOpenFiles": [
    "Untitled.md",
    "Linux Commands.md"
  ]
}